QQ_picture_operation/main.py
QQ_picture_operation/test.py
qq_picture_operation-0.1.0.dist-info/LICENSE
qq_picture_operation-0.1.0.dist-info/METADATA
qq_picture_operation-0.1.0.dist-info/WHEEL
qq_picture_operation-0.1.0.dist-info/RECORD
