Metadata-Version: 2.1
Name: qq-picture-operation
Version: 0.1.0
Summary: 进行qq图片的操作，用来转移复制删除图片 进行qq图片的操作，用来转移复制删除图片
License: MIT
Author: ziru-w
Author-email: 77319678+ziru-w@users.noreply.github.com
Requires-Python: >=3.6,<4.0
Classifier: License :: OSI Approved :: MIT License
Classifier: Programming Language :: Python :: 3
Classifier: Programming Language :: Python :: 3.6
Classifier: Programming Language :: Python :: 3.7
Classifier: Programming Language :: Python :: 3.8
Classifier: Programming Language :: Python :: 3.9
Classifier: Programming Language :: Python :: 3.10
Classifier: Programming Language :: Python :: 3.11
